{
    "labels": [
        "January",
        "February",
        "March",
        "April",
        "May",
        "June",
        "July"
    ],
    "datasets": [
        {
            "label": "My First dataset",
            "backgroundColor": "--blue-500",
            "borderColor": "--blue-500",
            "data": [
                65,
                59,
                80,
                81,
                56,
                55,
                40
            ]
        },
        {
            "label": "My Second dataset",
            "backgroundColor": "--pink-500",
            "borderColor": "--pink-500",
            "data": [
                28,
                48,
                40,
                19,
                86,
                27,
                90
            ]
        }
    ]
}